setup.cfg
setup.py
pyrcos/__init__.py
pyrcos/cmd.py
pyrcos/constants.py
pyrcos/functions.py
pyrcos/objects.py
pyrcos/utils.py
pyrcos.egg-info/PKG-INFO
pyrcos.egg-info/SOURCES.txt
pyrcos.egg-info/dependency_links.txt
pyrcos.egg-info/pbr.json
pyrcos.egg-info/requires.txt
pyrcos.egg-info/top_level.txt
pyrcos/datasets/__init__.py
pyrcos/datasets/protein_abundance.py
pyrcos/datasets/regulatory_network.py
pyrcos/datasets/tn_seq.py