Metadata-Version: 1.1
Name: pyrcos
Version: 0.0.1a1
Summary: Python hi-level interface for circos
Home-page: TBD
Author: Joao Cardoso
Author-email: jooaaoo@gmail.com
License: Apache License Version 2.0
Keywords: bioinformatics high-throughput
Platform: UNKNOWN
Classifier: Programming Language :: Python :: 3
Classifier: License :: OSI Approved :: Apache Software License
